ewoxservicefastapi/api_factory.py
ewoxservicefastapi/client/ioauth_client.py
ewoxservicefastapi/client/oauth_client.py
ewoxservicefastapi/examples/test_app.py
ewoxservicefastapi/examples/test_request_args.py
ewoxservicefastapi/examples/test_router.py
ewoxservicefastapi/middleware/dependency_injection.py
ewoxservicefastapi/middleware/jwt_auth.py
ewoxservicefastapi/middleware/rate_limitting.py
ewoxservicefastapi/models/request_model.py
ewoxservicefastapi/models/response_model.py
ewoxservicefastapi/models/user_oauth_model.py
ewoxservicefastapi/proto/proto_request_model.proto
ewoxservicefastapi/proto/proto_request_model_pb2.py
ewoxservicefastapi/proto/proto_response_model.proto
ewoxservicefastapi/proto/proto_response_model_pb2.py
ewoxservicefastapi/request_serializer.py
ewoxservicefastapi/response_serializer.py
ewoxservicefastapi/route_base_handler.py
ewoxservicefastapi/routers/keepalive.py
ewoxservicefastapi/service_app.py
ewoxservicefastapi-1.7.10.dist-info/METADATA
ewoxservicefastapi-1.7.10.dist-info/WHEEL
ewoxservicefastapi-1.7.10.dist-info/licenses/LICENSE
ewoxservicefastapi-1.7.10.dist-info/RECORD
