Metadata-Version: 2.4
Name: ewoxservicefastapi
Version: 1.7.10
Summary: 
License-File: LICENSE
Author: Martin Leo Prüss
Author-email: mleopruss@gmail.com
Requires-Python: >=3.9.9,<4.0.0
Classifier: Programming Language :: Python :: 3
Classifier: Programming Language :: Python :: 3.10
Classifier: Programming Language :: Python :: 3.11
Classifier: Programming Language :: Python :: 3.12
Classifier: Programming Language :: Python :: 3.13
Classifier: Programming Language :: Python :: 3.14
Requires-Dist: authlib (>=1.6.5,<2.0.0)
Requires-Dist: ewoxcore (>=1.6.2,<2.0.0)
Requires-Dist: fastapi (>=0.111.0,<0.112.0)
Requires-Dist: itsdangerous (>=2,<3)
Requires-Dist: jose (>=1.0.0,<2.0.0)
Requires-Dist: jsonpickle (>=4.1.1,<5.0.0)
Requires-Dist: lagom (>=2.6.0,<3.0.0)
Requires-Dist: protobuf (>=6.31.1,<7.0.0)
Requires-Dist: python-dateutil (>=2.9.0.post0,<3.0.0)
Requires-Dist: python-dotenv (>=1.1.1,<2.0.0)
Requires-Dist: python-i18n (>=0.3.9,<0.4.0)
Requires-Dist: python-jose[cryptography] (>=3.3.0,<4.0.0)
Requires-Dist: requests (>=2.32.4,<3.0.0)
Requires-Dist: sortedcontainers (>=2.4.0,<3.0.0)
Requires-Dist: uvicorn (>=0.30.0,<0.31.0)
Requires-Dist: uvloop (>=0.19.0,<0.20.0)
